{
  "nodeCount": 1,
  "agency": "Nuclear Regulatory Commission",
  "nodes": [
    {
      "name": "Areva, Inc.",
      "category": "Client",
      "amount": 1
    },
    {
      "name": "Nuclear Energy Strategies, LLC",
      "category": "Firm",
      "amount": 1
    },
    {
      "name": "Annie Caputo",
      "category": "Staffer",
      "amount": 1
    }
  ],
  "links": [
    {
      "source": 0,
      "target": 1,
      "value": 1
    },
    {
      "source": 1,
      "target": 2,
      "value": 1
    }
  ]
}